functions_by_vadeemkaa/README.md
functions_by_vadeemkaa/math_functions.py
functions_by_vadeemkaa-0.3.0.dist-info/WHEEL
functions_by_vadeemkaa-0.3.0.dist-info/METADATA
functions_by_vadeemkaa-0.3.0.dist-info/RECORD
